graphsTrees/__init__.py
graphsTrees/exceptions/EricExceptions.py
graphsTrees/exceptions/TreeExceptions.py
graphsTrees/exceptions/__init__.py
graphsTrees/graphs/__init__.py
graphsTrees/graphs/graphs.py
graphsTrees/graphs/wtGraphs.py
graphsTrees/trees/__init__.py
graphsTrees/trees/bst.py
graphsTrees/trees/node.py
graphsTrees/trees/tree.py
lab4GraphsTrees-0.1.dist-info/LICENCE.txt
lab4GraphsTrees-0.1.dist-info/METADATA
lab4GraphsTrees-0.1.dist-info/WHEEL
lab4GraphsTrees-0.1.dist-info/top_level.txt
lab4GraphsTrees-0.1.dist-info/RECORD
