Metadata-Version: 2.1
Name: lab4GraphsTrees
Version: 0.1
Summary: An assignment package for graph and tree data structures
Home-page: https://github.com/adityasal/DATA533_Lab4
Author: Eric Baxter, Aditya Saluja
Author-email: ebaxter1@hotmail.ca
License: MIT
Platform: UNKNOWN
